[
  {
    "artist": "Jah Prayzah",
    "title": "Ndini Mukudzeyi",
    "votes": 0,
    "streams": 0,
    "artworkUrl": "https://is1-ssl.mzstatic.com/image/thumb/Music211/v4/a0/57/d7/a057d756-2797-eab6-5037-7d55960fde18/artwork.jpg/300x300bb.jpg",
    "rank": 1,
    "prevRank": 1,
    "weeks": 18,
    "peak": 1,
    "trend": "—"
  },
  {
    "artist": "Celestial Chorus",
    "title": "Volume 2",
    "votes": 0,
    "streams": 0,
    "artworkUrl": "https://is1-ssl.mzstatic.com/image/thumb/Music211/v4/f8/87/be/f887bed9-65fd-2ffa-37c8-cb87f5f04e12/artwork.jpg/300x300bb.jpg",
    "rank": 2,
    "prevRank": 2,
    "weeks": 18,
    "peak": 2,
    "trend": "—"
  },
  {
    "artist": "Shona Prince",
    "title": "Pariah",
    "votes": 0,
    "streams": 0,
    "artworkUrl": "https://is1-ssl.mzstatic.com/image/thumb/Music211/v4/57/01/aa/5701aa61-e255-9093-2b2a-53ae949812aa/artwork.jpg/300x300bb.jpg",
    "rank": 3,
    "prevRank": 3,
    "weeks": 18,
    "peak": 3,
    "trend": "—"
  },
  {
    "artist": "Davido",
    "title": "5ive",
    "votes": 0,
    "streams": 0,
    "artworkUrl": "https://is1-ssl.mzstatic.com/image/thumb/Music211/v4/cd/0c/91/cd0c917a-e1a0-2592-a3a1-529796e19ea9/196872682564.jpg/300x300bb.jpg",
    "rank": 4,
    "prevRank": 4,
    "weeks": 18,
    "peak": 4,
    "trend": "—"
  },
  {
    "artist": "Dlala Thukzin",
    "title": "031 Studio Camp 2.0",
    "votes": 0,
    "streams": 0,
    "artworkUrl": "https://is1-ssl.mzstatic.com/image/thumb/Music221/v4/24/32/cd/2432cda8-5c09-c7f8-2af4-cc1106ccf1c3/6009553456870_Cover.jpg/300x300bb.jpg",
    "rank": 5,
    "prevRank": 5,
    "weeks": 18,
    "peak": 5,
    "trend": "—"
  },
  {
    "artist": "PARTYNEXTDOOR & Drake",
    "title": "$ome $exy $ongs 4 U",
    "votes": 0,
    "streams": 0,
    "artworkUrl": "https://is1-ssl.mzstatic.com/image/thumb/Music211/v4/34/10/1e/34101e1f-f4b9-907a-ce47-3fba5b3ee5e8/50222.jpg/300x300bb.jpg",
    "rank": 6,
    "prevRank": 6,
    "weeks": 18,
    "peak": 6,
    "trend": "—"
  },
  {
    "artist": "Jah Prayzah",
    "title": "Chiremerera",
    "votes": 0,
    "streams": 0,
    "artworkUrl": "https://is1-ssl.mzstatic.com/image/thumb/Music116/v4/b7/b6/35/b7b635b4-8145-10e9-22bc-1a15c54d2a7b/artwork.jpg/300x300bb.jpg",
    "rank": 7,
    "prevRank": 7,
    "weeks": 18,
    "peak": 7,
    "trend": "—"
  },
  {
    "artist": "Kabza De Small & Mthunzi",
    "title": "Isimo",
    "votes": 0,
    "streams": 0,
    "artworkUrl": "https://is1-ssl.mzstatic.com/image/thumb/Music126/v4/64/5b/c4/645bc49d-504c-8c1f-fa0a-6799643b946a/196871550000.jpg/300x300bb.jpg",
    "rank": 8,
    "prevRank": 8,
    "weeks": 18,
    "peak": 8,
    "trend": "—"
  },
  {
    "artist": "Playboi Carti",
    "title": "MUSIC - SORRY 4 DA WAIT",
    "votes": 0,
    "streams": 0,
    "artworkUrl": "https://is1-ssl.mzstatic.com/image/thumb/Music221/v4/fe/fc/f3/fefcf31a-4a86-9cc7-8e8e-9b777e6c6a40/25UMGIM46212.rgb.jpg/300x300bb.jpg",
    "rank": 9,
    "prevRank": 9,
    "weeks": 18,
    "peak": 9,
    "trend": "—"
  },
  {
    "artist": "Chris Brown",
    "title": "11:11 (Deluxe)",
    "votes": 0,
    "streams": 0,
    "artworkUrl": "https://is1-ssl.mzstatic.com/image/thumb/Music211/v4/2d/5c/c1/2d5cc1a6-86ce-ee16-5985-807f2fffa3cb/196871957267.jpg/300x300bb.jpg",
    "rank": 10,
    "prevRank": 10,
    "weeks": 18,
    "peak": 10,
    "trend": "—"
  },
  {
    "artist": "Jah Prayzah",
    "title": "Gwara",
    "votes": 0,
    "streams": 0,
    "artworkUrl": "https://is1-ssl.mzstatic.com/image/thumb/Music125/v4/5e/0d/b1/5e0db1b0-9582-40f0-c9fc-c399a81a3d6a/artwork.jpg/300x300bb.jpg",
    "rank": 11,
    "prevRank": 11,
    "weeks": 18,
    "peak": 11,
    "trend": "—"
  },
  {
    "artist": "Central Cee",
    "title": "CAN'T RUSH GREATNESS",
    "votes": 0,
    "streams": 0,
    "artworkUrl": "https://is1-ssl.mzstatic.com/image/thumb/Music211/v4/5a/7f/ef/5a7fefe9-5b4c-c72b-2446-6d4a0bc1d819/196872591545.jpg/300x300bb.jpg",
    "rank": 12,
    "prevRank": 12,
    "weeks": 18,
    "peak": 12,
    "trend": "—"
  },
  {
    "artist": "Minister Michael Mahendere & Direct Worship",
    "title": "Classical Worship, Vol. 3 (Nziyo Dzedu) [Live]",
    "votes": 0,
    "streams": 0,
    "artworkUrl": "https://is1-ssl.mzstatic.com/image/thumb/Music211/v4/2a/c8/85/2ac88507-233b-2b86-4382-ff17d83fe74b/859702075300_cover.jpg/300x300bb.jpg",
    "rank": 13,
    "prevRank": 13,
    "weeks": 18,
    "peak": 13,
    "trend": "—"
  },
  {
    "artist": "Kendrick Lamar",
    "title": "GNX",
    "votes": 0,
    "streams": 0,
    "artworkUrl": "https://is1-ssl.mzstatic.com/image/thumb/Music211/v4/50/c2/cc/50c2cc95-3658-9417-0d4b-831abde44ba1/24UM1IM28978.rgb.jpg/300x300bb.jpg",
    "rank": 14,
    "prevRank": 14,
    "weeks": 18,
    "peak": 14,
    "trend": "—"
  },
  {
    "artist": "Minister Michael Mahendere & Direct Worship",
    "title": "Getting Personal With God, Vol. 4",
    "votes": 0,
    "streams": 0,
    "artworkUrl": "https://is1-ssl.mzstatic.com/image/thumb/Music116/v4/e7/bf/08/e7bf08f4-7135-aaac-1a9a-34f5d0ce96aa/859752074407_cover.jpg/300x300bb.jpg",
    "rank": 15,
    "prevRank": 15,
    "weeks": 18,
    "peak": 15,
    "trend": "—"
  },
  {
    "artist": "DJ Maphorisa & Xduppy",
    "title": "NGOMOYA",
    "votes": 0,
    "streams": 0,
    "artworkUrl": "https://is1-ssl.mzstatic.com/image/thumb/Music221/v4/19/b3/ac/19b3ac87-bf66-0e45-2e2e-8c2c5c62510a/196872981476.jpg/300x300bb.jpg",
    "rank": 16,
    "prevRank": 16,
    "weeks": 18,
    "peak": 16,
    "trend": "—"
  },
  {
    "artist": "Mugaratia",
    "title": "Pemurai Dzose",
    "votes": 0,
    "streams": 0,
    "artworkUrl": "https://is1-ssl.mzstatic.com/image/thumb/Music221/v4/6f/ad/0f/6fad0f58-9f0c-68a4-df9b-e363eaff9a87/198999165685.jpg/300x300bb.jpg",
    "rank": 17,
    "prevRank": 17,
    "weeks": 18,
    "peak": 17,
    "trend": "—"
  },
  {
    "artist": "Gunna",
    "title": "One of Wun",
    "votes": 0,
    "streams": 0,
    "artworkUrl": "https://is1-ssl.mzstatic.com/image/thumb/Music221/v4/42/4e/45/424e4521-37b7-6f49-293a-98a1285ed7c5/075679660336.jpg/300x300bb.jpg",
    "rank": 18,
    "prevRank": 18,
    "weeks": 18,
    "peak": 18,
    "trend": "—"
  },
  {
    "artist": "Jah Prayzah",
    "title": "Maita Baba",
    "votes": 0,
    "streams": 0,
    "artworkUrl": "https://is1-ssl.mzstatic.com/image/thumb/Music126/v4/cd/03/90/cd039013-0025-56f5-0581-608c99c6ae7b/artwork.jpg/300x300bb.jpg",
    "rank": 19,
    "prevRank": 19,
    "weeks": 18,
    "peak": 19,
    "trend": "—"
  },
  {
    "artist": "Drake",
    "title": "Take Care (Deluxe Version)",
    "votes": 0,
    "streams": 0,
    "artworkUrl": "https://is1-ssl.mzstatic.com/image/thumb/Music125/v4/74/fb/d3/74fbd365-bd52-23b4-604b-7f164407b0a9/00602527899107.rgb.jpg/300x300bb.jpg",
    "rank": 20,
    "prevRank": 20,
    "weeks": 18,
    "peak": 20,
    "trend": "—"
  },
  {
    "artist": "Winky D",
    "title": "Gafa Futi",
    "votes": 0,
    "streams": 0,
    "artworkUrl": "https://is1-ssl.mzstatic.com/image/thumb/Music124/v4/6f/33/f9/6f33f930-8d4e-f68e-0fad-986086ac0417/artwork.jpg/300x300bb.jpg",
    "rank": 21,
    "prevRank": 21,
    "weeks": 18,
    "peak": 21,
    "trend": "—"
  },
  {
    "artist": "Drake",
    "title": "Certified Lover Boy",
    "votes": 0,
    "streams": 0,
    "artworkUrl": "https://is1-ssl.mzstatic.com/image/thumb/Music115/v4/11/36/38/1136384a-eebc-697a-c005-d890e41c0854/21UM1IM07518.rgb.jpg/300x300bb.jpg",
    "rank": 22,
    "prevRank": 22,
    "weeks": 18,
    "peak": 22,
    "trend": "—"
  },
  {
    "artist": "PARTYNEXTDOOR",
    "title": "PARTYNEXTDOOR 4 (P4)",
    "votes": 0,
    "streams": 0,
    "artworkUrl": "https://is1-ssl.mzstatic.com/image/thumb/Music211/v4/0d/de/c5/0ddec5e3-42f6-c550-6227-55dcd7d6b89a/39029.jpg/300x300bb.jpg",
    "rank": 23,
    "prevRank": 23,
    "weeks": 18,
    "peak": 23,
    "trend": "—"
  },
  {
    "artist": "Jah Prayzah",
    "title": "Hokoyo",
    "votes": 0,
    "streams": 0,
    "artworkUrl": "https://is1-ssl.mzstatic.com/image/thumb/Music114/v4/31/d3/e8/31d3e8ce-333f-a169-d6c0-95521e50ac95/696177616351_cover.jpg/300x300bb.jpg",
    "rank": 24,
    "prevRank": 24,
    "weeks": 18,
    "peak": 24,
    "trend": "—"
  },
  {
    "artist": "Voltz JT",
    "title": "N.O.P Makoni",
    "votes": 0,
    "streams": 0,
    "artworkUrl": "https://is1-ssl.mzstatic.com/image/thumb/Music221/v4/15/0e/64/150e64a0-db01-95a3-16fc-f0174b56f482/artwork.jpg/300x300bb.jpg",
    "rank": 25,
    "prevRank": 25,
    "weeks": 18,
    "peak": 25,
    "trend": "—"
  },
  {
    "artist": "Jah Prayzah",
    "title": "Chitubu",
    "votes": 0,
    "streams": 0,
    "artworkUrl": "https://is1-ssl.mzstatic.com/image/thumb/Music124/v4/a8/96/19/a8961935-c117-18a0-3fed-1763adc2a8de/195448136654.jpg/300x300bb.jpg",
    "rank": 26,
    "prevRank": 26,
    "weeks": 18,
    "peak": 26,
    "trend": "—"
  },
  {
    "artist": "Holy Ten",
    "title": "Proud Father",
    "votes": 0,
    "streams": 0,
    "artworkUrl": "https://is1-ssl.mzstatic.com/image/thumb/Music221/v4/53/ab/0f/53ab0f8f-ee02-3d9e-b7b6-7e27417e2271/198748915998-copy-704c7951.png/300x300bb.jpg",
    "rank": 27,
    "prevRank": 27,
    "weeks": 18,
    "peak": 27,
    "trend": "—"
  },
  {
    "artist": "Joyfull Praise Choir",
    "title": "Joyfull Praise 5 \"The Ark Project\"",
    "votes": 0,
    "streams": 0,
    "artworkUrl": "https://is1-ssl.mzstatic.com/image/thumb/Music221/v4/17/3b/32/173b324f-abf5-9e12-598e-1b3b382492e0/artwork.jpg/300x300bb.jpg",
    "rank": 28,
    "prevRank": 28,
    "weeks": 18,
    "peak": 28,
    "trend": "—"
  },
  {
    "artist": "Nutty O",
    "title": "Mustard Seed",
    "votes": 0,
    "streams": 0,
    "artworkUrl": "https://is1-ssl.mzstatic.com/image/thumb/Music125/v4/48/02/97/480297b8-1c72-bdd5-129d-44e921a1c36d/5059863695880_cover.jpg/300x300bb.jpg",
    "rank": 29,
    "prevRank": 29,
    "weeks": 18,
    "peak": 29,
    "trend": "—"
  },
  {
    "artist": "Bling4",
    "title": "Hosanna",
    "votes": 0,
    "streams": 0,
    "artworkUrl": "https://is1-ssl.mzstatic.com/image/thumb/Music221/v4/45/d8/b0/45d8b0a8-12ea-5dc9-9739-3d2f4151c174/artwork.jpg/300x300bb.jpg",
    "rank": 30,
    "prevRank": 30,
    "weeks": 15,
    "peak": 30,
    "trend": "—"
  },
  {
    "artist": "Saintfloew",
    "title": "Trap Yevafundisi",
    "votes": 0,
    "streams": 0,
    "artworkUrl": "https://is1-ssl.mzstatic.com/image/thumb/Music211/v4/a2/32/a8/a232a87a-3ca9-9d59-3bc9-fce406df1684/6009553447793_Cover.jpg/300x300bb.jpg",
    "rank": 31,
    "prevRank": 32,
    "weeks": 14,
    "peak": 31,
    "trend": "up"
  },
  {
    "artist": "Kelvin Momo",
    "title": "Thato Ya Modimo",
    "votes": 0,
    "streams": 0,
    "artworkUrl": "https://is1-ssl.mzstatic.com/image/thumb/Music221/v4/f2/5b/e4/f25be4cd-0105-1f7a-2e76-89cdb1221eb5/766214681052.png/300x300bb.jpg",
    "rank": 32,
    "prevRank": 33,
    "weeks": 12,
    "peak": 32,
    "trend": "up"
  },
  {
    "artist": "Drake",
    "title": "For All The Dogs Scary Hours Edition",
    "votes": 0,
    "streams": 0,
    "artworkUrl": "https://is1-ssl.mzstatic.com/image/thumb/Music126/v4/97/1a/a3/971aa332-2c7d-947c-33ed-4635d41115a4/23UM1IM56239.rgb.jpg/300x300bb.jpg",
    "rank": 33,
    "prevRank": 34,
    "weeks": 11,
    "peak": 33,
    "trend": "up"
  },
  {
    "artist": "Holy Ten",
    "title": "Musoro we Nzou",
    "votes": 0,
    "streams": 0,
    "artworkUrl": "https://is1-ssl.mzstatic.com/image/thumb/Music221/v4/37/e1/06/37e10617-1697-9a72-27d5-c00f93888048/199479153987.png/300x300bb.jpg",
    "rank": 34,
    "prevRank": 36,
    "weeks": 8,
    "peak": 34,
    "trend": "up"
  },
  {
    "artist": "Shona Prince",
    "title": "Pariah (Deluxe)",
    "votes": 0,
    "streams": 0,
    "artworkUrl": "https://is1-ssl.mzstatic.com/image/thumb/Music221/v4/50/ad/a8/50ada8bb-0823-2f61-3962-d9053b0bf37e/artwork.jpg/300x300bb.jpg",
    "rank": 35,
    "prevRank": 37,
    "weeks": 7,
    "peak": 35,
    "trend": "up"
  },
  {
    "artist": "YoungBoy Never Broke Again",
    "title": "MASA",
    "votes": 0,
    "streams": 0,
    "artworkUrl": "https://is1-ssl.mzstatic.com/image/thumb/Music211/v4/63/53/9a/63539a84-2e0d-717f-4ea8-8cd80bb71cf5/25UMGIM90753.rgb.jpg/300x300bb.jpg",
    "rank": 36,
    "prevRank": 38,
    "weeks": 7,
    "peak": 36,
    "trend": "up"
  },
  {
    "artist": "JACKBOYS & Travis Scott",
    "title": "JACKBOYS 2",
    "votes": 0,
    "streams": 0,
    "artworkUrl": "https://is1-ssl.mzstatic.com/image/thumb/Music221/v4/f0/ac/be/f0acbe98-e773-531e-3fd7-60716d4d2ff0/196873441108.jpg/300x300bb.jpg",
    "rank": 37,
    "prevRank": 39,
    "weeks": 6,
    "peak": 37,
    "trend": "up"
  },
  {
    "artist": "Clipse, Pusha T & Malice",
    "title": "Let God Sort Em Out",
    "votes": 0,
    "streams": 0,
    "artworkUrl": "https://is1-ssl.mzstatic.com/image/thumb/Music211/v4/70/a6/9a/70a69aeb-3bcf-968b-de75-f3cb44a89e1b/1605.jpg/300x300bb.jpg",
    "rank": 38,
    "prevRank": 40,
    "weeks": 6,
    "peak": 38,
    "trend": "up"
  },
  {
    "artist": "Kabza De Small",
    "title": "Bab'Motha",
    "votes": 0,
    "streams": 0,
    "artworkUrl": "https://is1-ssl.mzstatic.com/image/thumb/Music211/v4/56/68/86/56688681-7586-f2f7-7420-4e50e6f279a5/196873366234.jpg/300x300bb.jpg",
    "rank": 39,
    "prevRank": 41,
    "weeks": 5,
    "peak": 39,
    "trend": "up"
  },
  {
    "artist": "Kae Chaps",
    "title": "Tarantino",
    "votes": 0,
    "streams": 0,
    "artworkUrl": "https://is1-ssl.mzstatic.com/image/thumb/Music211/v4/16/87/b2/1687b218-a484-6bc4-1558-226e676bb7bb/artwork.jpg/300x300bb.jpg",
    "rank": 40,
    "prevRank": 42,
    "weeks": 5,
    "peak": 40,
    "trend": "up"
  },
  {
    "artist": "GIVĒON",
    "title": "BELOVED",
    "votes": 0,
    "streams": 0,
    "artworkUrl": "https://is1-ssl.mzstatic.com/image/thumb/Music221/v4/47/03/4c/47034c71-831b-61a2-8cc2-502f927834bd/196873057620.jpg/300x300bb.jpg",
    "rank": 41,
    "prevRank": 43,
    "weeks": 5,
    "peak": 41,
    "trend": "up"
  },
  {
    "artist": "Bagga",
    "title": "Truth - EP",
    "votes": 0,
    "streams": 0,
    "artworkUrl": "https://is1-ssl.mzstatic.com/image/thumb/Music211/v4/2b/85/31/2b853151-c0d6-c19d-0771-dd6e0d1c9bc0/198704645044_Cover.jpg/300x300bb.jpg",
    "rank": 42,
    "prevRank": 46,
    "weeks": 3,
    "peak": 42,
    "trend": "up"
  },
  {
    "artist": "Yeat",
    "title": "DANGEROUS SUMMER",
    "votes": 0,
    "streams": 0,
    "artworkUrl": "https://is1-ssl.mzstatic.com/image/thumb/Music221/v4/0e/1a/fc/0e1afc46-b47d-e2d2-e013-89ce92d5b9f5/25UM1IM02085.rgb.jpg/300x300bb.jpg",
    "rank": 43,
    "prevRank": 47,
    "weeks": 3,
    "peak": 43,
    "trend": "up"
  },
  {
    "artist": "Gunna",
    "title": "The Last Wun",
    "votes": 0,
    "streams": 0,
    "artworkUrl": "https://is1-ssl.mzstatic.com/image/thumb/Music211/v4/39/1e/0c/391e0c06-1536-a90f-7c49-06b9289c37e1/075679606358.jpg/300x300bb.jpg",
    "rank": 44,
    "prevRank": 49,
    "weeks": 2,
    "peak": 44,
    "trend": "up"
  },
  {
    "artist": "Mugaratia",
    "title": "Saladic Gangsta - EP",
    "votes": 0,
    "streams": 0,
    "artworkUrl": "https://is1-ssl.mzstatic.com/image/thumb/Music221/v4/b6/86/24/b6862430-99ce-583f-bbf2-70962949b9d1/199800276088.jpg/300x300bb.jpg",
    "rank": 45,
    "prevRank": 50,
    "weeks": 2,
    "peak": 45,
    "trend": "up"
  },
  {
    "artist": "Xduppy, Seun1401 & LastBornDiroba",
    "title": "Ghetto Fabulous EP",
    "votes": 0,
    "streams": 0,
    "artworkUrl": "https://is1-ssl.mzstatic.com/image/thumb/Music221/v4/30/79/19/3079193a-1d96-706f-3526-fe8c94b87138/196873479675.jpg/300x300bb.jpg",
    "rank": 46,
    "prevRank": null,
    "weeks": 1,
    "peak": 46,
    "trend": "new"
  },
  {
    "artist": "JID",
    "title": "God Does Like Ugly",
    "votes": 0,
    "streams": 0,
    "artworkUrl": "https://is1-ssl.mzstatic.com/image/thumb/Music221/v4/7b/e1/66/7be166a3-92e6-c505-0802-9599973629ea/25UMGIM55109.rgb.jpg/300x300bb.jpg",
    "rank": 47,
    "prevRank": null,
    "weeks": 1,
    "peak": 47,
    "trend": "new"
  },
  {
    "artist": "Nasty C",
    "title": "Free",
    "votes": 0,
    "streams": 0,
    "artworkUrl": "https://is1-ssl.mzstatic.com/image/thumb/Music221/v4/c1/dc/62/c1dc62bb-0a1d-da69-3ede-59a2f5ca99a9/5059449230801.png/300x300bb.jpg",
    "rank": 48,
    "prevRank": null,
    "weeks": 1,
    "peak": 48,
    "trend": "new"
  },
  {
    "artist": "Shekhinah",
    "title": "Less Trouble",
    "votes": 0,
    "streams": 0,
    "artworkUrl": "https://is1-ssl.mzstatic.com/image/thumb/Music211/v4/03/b6/9c/03b69cad-0308-c8c7-b73b-147568964128/859713107281_cover.jpg/300x300bb.jpg",
    "rank": 49,
    "prevRank": null,
    "weeks": 1,
    "peak": 49,
    "trend": "new"
  },
  {
    "artist": "Tyla",
    "title": "WWP - Single",
    "votes": 0,
    "streams": 0,
    "artworkUrl": "https://is1-ssl.mzstatic.com/image/thumb/Music211/v4/8e/dc/d6/8edcd6ad-068b-b33f-0f13-44e20e07bdbe/196873431987.jpg/300x300bb.jpg",
    "rank": 50,
    "prevRank": null,
    "weeks": 1,
    "peak": 50,
    "trend": "new"
  }
]